{
	"interactionModel": {
		"languageModel": {
			"invocationName": "fechadura inteligente",
			"types": [
				{
					"name": "lockInputType",
					"values": [
						{
							"id": null,
							"name": {
								"value": "trancar",
								"synonyms": [
									"fechar",
									"travar",
									"trancar",
									"fecha",
									"trava",
									"tranque",
									"trancasse",
									"fechasse",
									"feche"
								]
							}
						},
						{
							"id": null,
							"name": {
								"value": "destrancar",
								"synonyms": [
									"abrir",
									"destravar",
									"abrisse",
									"abra"
								]
							}
						}
					]
				}
			],
			"intents": [
				{
					"name": "HelloIntent",
					"samples": [
						"oi",
						"olá"
					]
				},
				{
					"name": "LockIntent",
					"samples": [
						"{lockStatus}",
						"por favor {lockStatus} a porta",
						"{lockStatus} a porta",
						"poderia {lockStatus}",
						"gostaria que {lockStatus} a porta",
						"pode {lockStatus} a porta",
						"quero {lockStatus} a porta",
						"faça {lockStatus}"
					],
					"slots": [
						{
							"name": "lockStatus",
							"type": "lockInputType"
						}
					]
				},
				{
					"name": "AMAZON.CancelIntent",
					"samples": []
				},
				{
					"name": "AMAZON.HelpIntent",
					"samples": []
				},
				{
					"name": "AMAZON.StopIntent",
					"samples": []
				}
			]
		}
	}
}